{
    "icon" : "favicon.ico",
    "path" : "",
    "stylesheets" : [
        "css/bootstrap-3.3.5-custom.css",
        "css/structure.css",
        "css/theme.css"
    ],
    "settings" : {
        "logo" : {
            "src" : "images/logo.png",
            "title" : "OpenMDM",
            "width": "210px",
            "alt" : "OpenMDM"
        },
        "loginLogo" : {
            "src" : "images/logo.png",
            "title" : "OpenMDM",
            "alt" : "OpenMDM",
            "width" : "310px"
        },
        "footer" : {
            "mailto" : "open-identity-platform-openidm@googlegroups.com"
        }
    }
}
